log_storage/__init__.py
log_storage/admin.py
log_storage/models.py
log_storage/tests.py
log_storage/migrations/0001_initial.py
log_storage/migrations/__init__.py
log_storage-0.10.0.dist-info/LICENSE
log_storage-0.10.0.dist-info/METADATA
log_storage-0.10.0.dist-info/WHEEL
log_storage-0.10.0.dist-info/top_level.txt
log_storage-0.10.0.dist-info/RECORD
