Metadata-Version: 2.1
Name: log-storage
Version: 0.10.0
Summary: Log handler to store messages with a database record and optional file storage.
Home-page: https://github.com/virtualstock/log_storage/
Author: Virtualstock
Author-email: development.team@virtualstock.com
License: MIT
Keywords: Django,Log,App
Platform: UNKNOWN
Requires-Dist: django
Requires-Dist: django-private-storage
